dane_jwe_jws/__init__.py
dane_jwe_jws/authentication.py
dane_jwe_jws/encryption.py
dane_jwe_jws/util.py
dane_jwe_jws-0.12.dist-info/LICENSE
dane_jwe_jws-0.12.dist-info/METADATA
dane_jwe_jws-0.12.dist-info/WHEEL
dane_jwe_jws-0.12.dist-info/top_level.txt
dane_jwe_jws-0.12.dist-info/RECORD
