Metadata-Version: 2.1
Name: dane-jwe-jws
Version: 0.12
Summary: A library for using DANE for identity-secured JWE and JWS.
Home-page: https://github.com/valimail/dane_jwe_jws
Author: Ash Wilson
Author-email: ash.d.wilson@gmail.com
License: BSD
Keywords: dane tlsa dns jwe jws
Platform: UNKNOWN
Classifier: Development Status :: 4 - Beta
Classifier: Intended Audience :: Developers
Classifier: Operating System :: MacOS :: MacOS X
Classifier: Operating System :: POSIX :: Linux
Classifier: Programming Language :: Python :: 3.7
Classifier: Topic :: Security
Classifier: License :: OSI Approved :: BSD License
License-File: LICENSE
Requires-Dist: dane-discovery (==0.20)
Requires-Dist: jwcrypto (<2.0,>=0.7)
